kgraphplanner/__init__.py
kgraphplanner/kgraph_planner.py
kgraphplanner/agent/__init__.py
kgraphplanner/agent/kg_planning_agent.py
kgraphplanner/agent/kg_planning_base_agent.py
kgraphplanner/agent/kg_planning_inter_agent.py
kgraphplanner/agent/kg_planning_internal_structured_agent.py
kgraphplanner/agent/kg_planning_structured_agent.py
kgraphplanner/agent/kgraph_agent.py
kgraphplanner/agent/kgraph_base_agent.py
kgraphplanner/agent/kgraph_case_agent.py
kgraphplanner/agent/kgraph_chat_agent.py
kgraphplanner/agent/kgraph_exec_graph_agent.py
kgraphplanner/agent/kgraph_planner_agent.py
kgraphplanner/agent/kgraph_reasoning_agent.py
kgraphplanner/agent/kgraph_tool_agent.py
kgraphplanner/agent/kgraphplanner_agent.py
kgraphplanner/agent/tool_executor.py
kgraphplanner/agent/tool_node.py
kgraphplanner/agent/tool_validator.py
kgraphplanner/checkpointer/__init__.py
kgraphplanner/checkpointer/kgraph_serialized.py
kgraphplanner/checkpointer/kgraph_serializer.py
kgraphplanner/checkpointer/kgraphmemory_checkpointer.py
kgraphplanner/checkpointer/kgraphservice_checkpointer.py
kgraphplanner/checkpointer/kgservice_checkpointer.py
kgraphplanner/checkpointer/memory_checkpointer.py
kgraphplanner/config/__init__.py
kgraphplanner/config/agent_config.py
kgraphplanner/graph/__init__.py
kgraphplanner/graph/exec_graph.py
kgraphplanner/inter/__init__.py
kgraphplanner/inter/base_agent_schema.py
kgraphplanner/inter/generate_agent_schema.py
kgraphplanner/inter/agents/__init__.py
kgraphplanner/inter/agents/agent_weather/__init__.py
kgraphplanner/inter/agents/agent_weather/agent_weather_schema.py
kgraphplanner/planner/__init__.py
kgraphplanner/planner/kgraph_planner.py
kgraphplanner/preset/__init__.py
kgraphplanner/preset/agent/__init__.py
kgraphplanner/preset/agent/base_tool_agent.py
kgraphplanner/preset/agent/case_agent.py
kgraphplanner/preset/agent/chat_agent.py
kgraphplanner/preset/worker/__init__.py
kgraphplanner/preset/worker/chat_worker.py
kgraphplanner/preset/worker/weather_worker.py
kgraphplanner-0.0.15.dist-info/LICENSE
kgraphplanner-0.0.15.dist-info/METADATA
kgraphplanner-0.0.15.dist-info/WHEEL
kgraphplanner-0.0.15.dist-info/top_level.txt
kgraphplanner-0.0.15.dist-info/RECORD
