Metadata-Version: 2.1
Name: kgraphplanner
Version: 0.0.15
Summary: KGraph Planner
Home-page: https://github.com/vital-ai/kgraphplanner
Author: Marc Hadfield
Author-email: marc@vital.ai
License: Apache License 2.0
Classifier: Programming Language :: Python :: 3.12
Classifier: License :: OSI Approved :: Apache Software License
Classifier: Operating System :: OS Independent
Requires-Python: >=3.12
License-File: LICENSE
Requires-Dist: vital-ai-vitalsigns>=0.1.32
Requires-Dist: vital-ai-aimp>=0.1.16
Requires-Dist: vital-ai-haley-kg>=0.1.24
Requires-Dist: langchain-openai>=0.3.32
Requires-Dist: langgraph>=0.6.6
Requires-Dist: langgraph-checkpoint>=2.1.1
Requires-Dist: vital-agent-kg-utils>=0.1.7
Requires-Dist: python-dotenv
Requires-Dist: rich>=13.7.1
Provides-Extra: dev
Requires-Dist: twine; extra == "dev"
Requires-Dist: setuptools; extra == "dev"
Requires-Dist: pygraphviz; extra == "dev"
Requires-Dist: nest-asyncio; extra == "dev"
Requires-Dist: pyppeteer; extra == "dev"
